springernature_api/__init__.py
springernature_api/api_client.py
springernature_api/config.py
springernature_api/exceptions.py
springernature_api/logging_config.py
springernature_api/meta.py
springernature_api/metadata.py
springernature_api/openaccess.py
springernature_api/tdm.py
springernature_api/utils.py
springernature_api/version.py
springernature_api-0.1.0.dist-info/LICENSE
springernature_api-0.1.0.dist-info/METADATA
springernature_api-0.1.0.dist-info/WHEEL
springernature_api-0.1.0.dist-info/top_level.txt
springernature_api-0.1.0.dist-info/RECORD
